FISHcreation/__init__.py
FISHcreation/src/__init__.py
FISHcreation/src/preprocess.py
FISHcreation/src/process_boxes.py
FISHcreation/src/signals.py
FISHcreation/src/utils.py
FISHcreation-1.0.dist-info/METADATA
FISHcreation-1.0.dist-info/WHEEL
FISHcreation-1.0.dist-info/top_level.txt
FISHcreation-1.0.dist-info/RECORD
