Metadata-Version: 2.1
Name: FISHcreation
Version: 1.0
Home-page: https://github.com/SimonBon/FISHcreation
Author: Simon Gutwein
Author-email: simon.gutwein@ccri.at
License: MIT
Classifier: License :: OSI Approved :: MIT License
Classifier: Programming Language :: Python
Classifier: Programming Language :: Python :: 3
Classifier: Programming Language :: Python :: 3.9
Requires-Dist: cellplot
Requires-Dist: cellpatchextraction
Requires-Dist: scipy
Requires-Dist: numpy
Requires-Dist: h5py
Requires-Dist: torch
